vfsfusepy/__init__.py
vfsfusepy/__main__.py
vfsfusepy/file_operations.py
vfsfusepy/git_operations.py
vfsfusepy/utils.py
vfsfusepy/version.py
vfsfusepy/vfs.py
vfsfusepy-0.4.1.dist-info/LICENSE
vfsfusepy-0.4.1.dist-info/METADATA
vfsfusepy-0.4.1.dist-info/WHEEL
vfsfusepy-0.4.1.dist-info/entry_points.txt
vfsfusepy-0.4.1.dist-info/top_level.txt
vfsfusepy-0.4.1.dist-info/RECORD
