Metadata-Version: 2.1
Name: vfsfusepy
Version: 0.4.1
Summary: A versioned file system based on FUSE and Git.
Home-page: https://github.com/nero19960329/VFS-FUSE
Author: Zhao Wang
Author-email: wangzhao2013tsinghua@gmail.com
License: MIT
Classifier: Development Status :: 3 - Alpha
Classifier: Intended Audience :: Developers
Classifier: License :: OSI Approved :: MIT License
Classifier: Programming Language :: Python :: 3.7
Classifier: Programming Language :: Python :: 3.8
Classifier: Programming Language :: Python :: 3.9
Classifier: Programming Language :: Python :: 3.10
Requires-Python: >=3.7
License-File: LICENSE
Requires-Dist: GitPython
Requires-Dist: argparse
Requires-Dist: loguru
Requires-Dist: fusepy
